{
  "parent": "minecraft:recipes/root",
  "criteria": {
    "has_dim_peach_block": {
      "conditions": {
        "items": [
          {
            "items": "luminax:dim_peach_block"
          }
        ]
      },
      "trigger": "minecraft:inventory_changed"
    },
    "has_the_recipe": {
      "conditions": {
        "recipe": "luminax:dim_peach_stairs"
      },
      "trigger": "minecraft:recipe_unlocked"
    }
  },
  "requirements": [
    [
      "has_the_recipe",
      "has_dim_peach_block"
    ]
  ],
  "rewards": {
    "recipes": [
      "luminax:dim_peach_stairs"
    ]
  }
}